gdb_call_lambda/__init__.py
gdb_call_lambda-0.0.2.dist-info/LICENSE
gdb_call_lambda-0.0.2.dist-info/METADATA
gdb_call_lambda-0.0.2.dist-info/WHEEL
gdb_call_lambda-0.0.2.dist-info/top_level.txt
gdb_call_lambda-0.0.2.dist-info/zip-safe
gdb_call_lambda-0.0.2.dist-info/RECORD
