Metadata-Version: 2.1
Name: gdb-call-lambda
Version: 0.0.2
Summary: Call C++ lambda functions from gdb
Home-page: UNKNOWN
Author: user202729
License: GNU General Public License v3 or later (GPLv3+)
Platform: UNKNOWN
